robotframework_auto_screenshot_listener/ScreenshotListener.py
robotframework_auto_screenshot_listener/__init__.py
robotframework_auto_screenshot_listener-0.1.8.dist-info/METADATA
robotframework_auto_screenshot_listener-0.1.8.dist-info/WHEEL
robotframework_auto_screenshot_listener-0.1.8.dist-info/top_level.txt
robotframework_auto_screenshot_listener-0.1.8.dist-info/RECORD
