Metadata-Version: 2.4
Name: robotframework-auto-screenshot-listener
Version: 0.1.8
Summary: A Robot Framework listener that automatically takes screenshots before each keyword.
Author-email: Jagadeesh Vedula <vedulajagadeesh1994@gmail.com>
Project-URL: Homepage, https://github.com/JagadeeshVedula/Robot-Screenshot-Listener
Project-URL: Bug Tracker, https://github.com/JagadeeshVedula/Robot-Screenshot-Listener/issues
Classifier: Programming Language :: Python :: 3
Classifier: License :: OSI Approved :: MIT License
Classifier: Operating System :: OS Independent
Classifier: Framework :: Robot Framework
Classifier: Topic :: Software Development :: Testing
Requires-Python: >=3.8
Requires-Dist: robotframework>=5.0
Requires-Dist: robotframework-seleniumlibrary>=6.2.0
